dynamodb_pep249/__init__.py
dynamodb_pep249-0.1.0.dist-info/LICENSE
dynamodb_pep249-0.1.0.dist-info/METADATA
dynamodb_pep249-0.1.0.dist-info/WHEEL
dynamodb_pep249-0.1.0.dist-info/top_level.txt
dynamodb_pep249-0.1.0.dist-info/RECORD
