Metadata-Version: 2.1
Name: dynamodb-pep249
Version: 0.1.0
Summary: PEP249 Database wrapper for DynamoDB
Home-page: https://github.com/willemt/dyanamodb-pep249
Author: willemt
Author-email: himself@willemthiart.com
License: BSD
Keywords: development logging
Platform: UNKNOWN
Classifier: Development Status :: 3 - Alpha
Classifier: Intended Audience :: Developers
Classifier: Topic :: System :: Logging
Classifier: License :: OSI Approved :: BSD License
Classifier: Programming Language :: Python :: 3.7
Requires-Dist: pynamodb
